mango_pycore/api/__init__.py
mango_pycore/api/base_api.py
mango_pycore/api/exceptions.py
mango_pycore/api/http_api.py
mango_pycore/api/request.py
mango_pycore/api/response.py
mango_pycore/api/rest_api.py
mango_pycore/api/websocket_api.py
mango_pycore/docs/Makefile
mango_pycore/docs/_build/doctrees/api.doctree
mango_pycore/docs/_build/doctrees/environment.pickle
mango_pycore/docs/_build/doctrees/environment_data.adapters.doctree
mango_pycore/docs/_build/doctrees/environment_data.doctree
mango_pycore/docs/_build/doctrees/environment_data.services.doctree
mango_pycore/docs/_build/doctrees/helloworld.doctree
mango_pycore/docs/_build/doctrees/index.doctree
mango_pycore/docs/_build/doctrees/instalation.doctree
mango_pycore/docs/_build/doctrees/modules.doctree
mango_pycore/docs/_build/doctrees/objects.doctree
mango_pycore/docs/_build/doctrees/restTutorial.doctree
mango_pycore/docs/_build/doctrees/stream.doctree
mango_pycore/docs/_build/doctrees/tools.doctree
mango_pycore/docs/_build/doctrees/triggers.doctree
mango_pycore/docs/_build/doctrees/websocket.doctree
mango_pycore/docs/_build/doctrees/websocketTutorial.doctree
mango_pycore/docs/_build/html/.buildinfo
mango_pycore/docs/_build/html/_modules/api/exceptions.html
mango_pycore/docs/_build/html/_modules/api/http_api.html
mango_pycore/docs/_build/html/_modules/api/rest_api.html
mango_pycore/docs/_build/html/_modules/api/websocket_api.html
mango_pycore/docs/_build/html/_modules/environment_data/adapters/access_control_adapter.html
mango_pycore/docs/_build/html/_modules/environment_data/adapters/s3_environment_adapter.html
mango_pycore/docs/_build/html/_modules/environment_data/services/audit_service.html
mango_pycore/docs/_build/html/_modules/index.html
mango_pycore/docs/_build/html/_modules/objects/user.html
mango_pycore/docs/_build/html/_modules/tools/utils.html
mango_pycore/docs/_build/html/_modules/websocket/client.html
mango_pycore/docs/_build/html/_sources/api.rst.txt
mango_pycore-0.1.38.dist-info/METADATA
mango_pycore-0.1.38.dist-info/WHEEL
mango_pycore-0.1.38.dist-info/RECORD
