Metadata-Version: 2.3
Name: mango-pycore
Version: 0.1.38
Summary: 
Author: Ernesto Licea Martin
Author-email: ernesto.licea@mango-soft.com
Requires-Python: >=3.9,<4.0
Classifier: Programming Language :: Python :: 3
Classifier: Programming Language :: Python :: 3.9
Classifier: Programming Language :: Python :: 3.10
Classifier: Programming Language :: Python :: 3.11
Classifier: Programming Language :: Python :: 3.12
Classifier: Programming Language :: Python :: 3.13
Requires-Dist: boto3 (>=1.26.111,<2.0.0)
Requires-Dist: pycryptodome (>=3.19.0,<4.0.0)
Requires-Dist: requests (>=2.31.0,<3.0.0)
Requires-Dist: rsa (>=4.9,<5.0)
Requires-Dist: websockets (>=11.0.1,<12.0.0)
